README.rst
setup.py
ebcloudstore/__init__.py
ebcloudstore/client.py
ebcloudstore/util.py
ebcloudstore.egg-info/PKG-INFO
ebcloudstore.egg-info/SOURCES.txt
ebcloudstore.egg-info/dependency_links.txt
ebcloudstore.egg-info/requires.txt
ebcloudstore.egg-info/top_level.txt