Metadata-Version: 1.1
Name: ebcloudstore
Version: 1.3
Summary: 53iq cloud store
Home-page: https://open.53iq.com/guide
Author: zdw
Author-email: tsengdavid@126.com
License: http://www.apache.org/licenses/LICENSE-2.0
Keywords: 53iq,xingji,ebanswers
Platform: UNKNOWN
Classifier: Programming Language :: Python :: 3
Classifier: License :: OSI Approved :: Apache Software License
